pyappstoreconnect/__init__.py
pyappstoreconnect/appAnalytics.py
pyappstoreconnect/benchmarks.py
pyappstoreconnect/client.py
pyappstoreconnect/metricsWithFilter.py
pyappstoreconnect/metricsWithGroup.py
pyappstoreconnect/settings.py
pyappstoreconnect/timeSeriesAnalytics.py
pyappstoreconnect-2.0.0.dist-info/LICENSE
pyappstoreconnect-2.0.0.dist-info/METADATA
pyappstoreconnect-2.0.0.dist-info/WHEEL
pyappstoreconnect-2.0.0.dist-info/top_level.txt
pyappstoreconnect-2.0.0.dist-info/RECORD
