Metadata-Version: 2.1
Name: pyappstoreconnect
Version: 2.0.0
Author-email: Grigory Efimov <grigory.efimov@gmail.com>
Maintainer-email: Grigory Efimov <grigory.efimov@gmail.com>
License: MIT License
Project-URL: Homepage, https://github.com/fb929/pyappstoreconnect
Project-URL: Documentation, https://github.com/fb929/pyappstoreconnect
Project-URL: Repository, https://github.com/fb929/pyappstoreconnect
License-File: LICENSE
Requires-Dist: python-sirp >=1.0.2
